install/__init__.py
install/createKernel.py
install/generate.py
install/pixiedustapp.py
pixiedust/__init__.py
pixiedust/proxyShell.py
pixiedust/apps/__init__.py
pixiedust/apps/cfBrowser.py
pixiedust/apps/cloudantBrowser.py
pixiedust/apps/connectionWidget.py
pixiedust/apps/mapboxBase.py
pixiedust/apps/mongoBrowser.py
pixiedust/apps/messageHub/__init__.py
pixiedust/apps/messageHub/messageHubApp.py
pixiedust/apps/watsonML/__init__.py
pixiedust/apps/watsonML/watsonMLApp.py
pixiedust/display/__init__.py
pixiedust/display/display.py
pixiedust/display/app/__init__.py
pixiedust/display/app/pixieapp.py
pixiedust/display/chart/__init__.py
pixiedust/display/chart/colorManager.py
pixiedust/display/chart/display.py
pixiedust/display/chart/plugins/__init__.py
pixiedust/display/chart/plugins/chart.py
pixiedust/display/chart/plugins/dialog.py
pixiedust/display/chart/plugins/elementInfo.py
pixiedust/display/chart/renderers/__init__.py
pixiedust/display/chart/renderers/baseChartDisplay.py
pixiedust/display/chart/renderers/commonOptions.py
pixiedust/display/chart/renderers/bokeh/__init__.py
pixiedust/display/chart/renderers/bokeh/barChartDisplay.py
pixiedust/display/chart/renderers/bokeh/bokehBaseDisplay.py
pixiedust/display/chart/renderers/bokeh/histogramDisplay.py
pixiedust/display/chart/renderers/bokeh/lineChartDisplay.py
pixiedust/display/chart/renderers/bokeh/scatterPlotDisplay.py
pixiedust/display/chart/renderers/google/__init__.py
pixiedust/display/chart/renderers/google/googleBaseDisplay.py
pixiedust/display/chart/renderers/google/googleMapDisplay.py
pixiedust/display/chart/renderers/google/templates/mapView.html
pixiedust/display/chart/renderers/google/templates/mapView.js
pixiedust/display/chart/renderers/google/templates/mapViewOptionsDialogBody.html
pixiedust/display/chart/renderers/google/templates/noapikey.html
pixiedust/display/chart/renderers/mapbox/__init__.py
pixiedust/display/chart/renderers/mapbox/mapBoxBaseDisplay.py
pixioptimus-1.0.10.dist-info/DESCRIPTION.rst
pixioptimus-1.0.10.dist-info/METADATA
pixioptimus-1.0.10.dist-info/RECORD
pixioptimus-1.0.10.dist-info/WHEEL
pixioptimus-1.0.10.dist-info/metadata.json
pixioptimus-1.0.10.dist-info/top_level.txt
