Metadata-Version: 2.0
Name: pixioptimus
Version: 1.0.10
Summary: Productivity library for Spark Python Notebook
Home-page: https://github.com/FavioVazquez/pixiedust-optimus
Author: David Taieb - Favio Vazquez
Author-email: david_taieb@us.ibm.com
License: Apache 2.0
Platform: UNKNOWN
Requires-Dist: geojson
Requires-Dist: lxml
Requires-Dist: mpld3
